{"hash":"a45386445bf7e6ab4d69","version":"5.75.0","time":5780,"builtAt":1678068121771,"publicPath":"auto","outputPath":"./reports/size","assetsByChunkName":{"index":["web.js"]},"assets":[{"type":"asset","name":"web.js","size":518053,"emitted":false,"comparedForEmit":true,"cached":false,"info":{"javascriptModule":false,"minimized":true,"related":{"license":"web.js.LICENSE.txt"},"size":518053},"chunkNames":["index"],"chunkIdHints":[],"auxiliaryChunkNames":[],"auxiliaryChunkIdHints":[],"filteredRelated":0,"related":[{"type":"license","name":"web.js.LICENSE.txt","size":146,"emitted":false,"comparedForEmit":true,"cached":false,"info":{"extractedComments":true,"size":146},"chunkNames":[],"chunkIdHints":[],"auxiliaryChunkNames":[],"auxiliaryChunkIdHints":[],"related":{},"chunks":[],"auxiliaryChunks":[],"isOverSizeLimit":false}],"chunks":[826],"auxiliaryChunks":[],"isOverSizeLimit":true}],"chunks":[{"rendered":true,"initial":true,"entry":true,"recorded":false,"size":521062,"sizes":{"javascript":521062},"names":["index"],"idHints":[],"runtime":["index"],"files":["web.js"],"auxiliaryFiles":[],"hash":"44b96393fba8371a01cb","childrenByOrder":{},"id":826,"siblings":[],"parents":[],"children":[],"modules":[{"type":"module","moduleType":"javascript/auto","layer":null,"size":10313,"sizes":{"javascript":10313},"built":true,"codeGenerated":true,"buildTimeExecuted":false,"cached":false,"identifier":"./dist/static/js/main.c29064ae.js","name":"./dist/static/js/main.c29064ae.js","nameForCondition":"./dist/static/js/main.c29064ae.js","index":0,"preOrderIndex":0,"index2":0,"postOrderIndex":0,"cacheable":true,"optional":false,"orphan":false,"dependent":false,"issuer":null,"issuerName":null,"issuerPath":null,"failed":false,"errors":0,"warnings":0,"id":31,"issuerId":null,"chunks":[826],"assets":[],"reasons":[{"moduleIdentifier":null,"module":null,"moduleName":null,"resolvedModuleIdentifier":null,"resolvedModule":null,"type":"entry","active":true,"explanation":"","userRequest":"./dist/static/js/main.c29064ae.js","loc":"index","moduleId":null,"resolvedModuleId":null}],"usedExports":[],"providedExports":null,"optimizationBailout":["Statement (ExpressionStatement) with side effects in source code at 2:13-10200","ModuleConcatenation bailout: Module is not an ECMAScript module"],"depth":0},{"type":"module","moduleType":"javascript/auto","layer":null,"size":2020,"sizes":{"javascript":2020},"built":true,"codeGenerated":true,"buildTimeExecuted":false,"cached":false,"identifier":"./dist/static/js/runtime.cb956988.js","name":"./dist/static/js/runtime.cb956988.js","nameForCondition":"./dist/static/js/runtime.cb956988.js","index":1,"preOrderIndex":1,"index2":1,"postOrderIndex":1,"cacheable":true,"optional":false,"orphan":false,"dependent":false,"issuer":null,"issuerName":null,"issuerPath":null,"failed":false,"errors":0,"warnings":0,"id":648,"issuerId":null,"chunks":[826],"assets":[],"reasons":[{"moduleIdentifier":null,"module":null,"moduleName":null,"resolvedModuleIdentifier":null,"resolvedModule":null,"type":"entry","active":true,"explanation":"","userRequest":"./dist/static/js/runtime.cb956988.js","loc":"index","moduleId":null,"resolvedModuleId":null}],"usedExports":[],"providedExports":null,"optimizationBailout":["Statement (ExpressionStatement) with side effects in source code at 1:0-1975","ModuleConcatenation bailout: Module is not an ECMAScript module"],"depth":0},{"type":"module","moduleType":"javascript/auto","layer":null,"size":508729,"sizes":{"javascript":508729},"built":true,"codeGenerated":true,"buildTimeExecuted":false,"cached":false,"identifier":"./dist/static/js/vendors.365dc8b1.js","name":"./dist/static/js/vendors.365dc8b1.js","nameForCondition":"./dist/static/js/vendors.365dc8b1.js","index":2,"preOrderIndex":2,"index2":2,"postOrderIndex":2,"cacheable":true,"optional":false,"orphan":false,"dependent":false,"issuer":null,"issuerName":null,"issuerPath":null,"failed":false,"errors":0,"warnings":0,"id":754,"issuerId":null,"chunks":[826],"assets":[],"reasons":[{"moduleIdentifier":null,"module":null,"moduleName":null,"resolvedModuleIdentifier":null,"resolvedModule":null,"type":"entry","active":true,"explanation":"","userRequest":"./dist/static/js/vendors.365dc8b1.js","loc":"index","moduleId":null,"resolvedModuleId":null}],"usedExports":[],"providedExports":null,"optimizationBailout":["Statement (ExpressionStatement) with side effects in source code at 2:0-508607","ModuleConcatenation bailout: Module is not an ECMAScript module"],"depth":0}],"origins":[{"module":"","moduleIdentifier":"","moduleName":"","loc":"index","request":"./dist/static/js/main.c29064ae.js"},{"module":"","moduleIdentifier":"","moduleName":"","loc":"index","request":"./dist/static/js/runtime.cb956988.js"},{"module":"","moduleIdentifier":"","moduleName":"","loc":"index","request":"./dist/static/js/vendors.365dc8b1.js"}]}],"modules":[{"type":"module","moduleType":"javascript/auto","layer":null,"size":10313,"sizes":{"javascript":10313},"built":true,"codeGenerated":true,"buildTimeExecuted":false,"cached":false,"identifier":"./dist/static/js/main.c29064ae.js","name":"./dist/static/js/main.c29064ae.js","nameForCondition":"./dist/static/js/main.c29064ae.js","index":0,"preOrderIndex":0,"index2":0,"postOrderIndex":0,"cacheable":true,"optional":false,"orphan":false,"issuer":null,"issuerName":null,"issuerPath":null,"failed":false,"errors":0,"warnings":0,"id":31,"issuerId":null,"chunks":[826],"assets":[],"reasons":[{"moduleIdentifier":null,"module":null,"moduleName":null,"resolvedModuleIdentifier":null,"resolvedModule":null,"type":"entry","active":true,"explanation":"","userRequest":"./dist/static/js/main.c29064ae.js","loc":"index","moduleId":null,"resolvedModuleId":null}],"usedExports":[],"providedExports":null,"optimizationBailout":["Statement (ExpressionStatement) with side effects in source code at 2:13-10200","ModuleConcatenation bailout: Module is not an ECMAScript module"],"depth":0},{"type":"module","moduleType":"javascript/auto","layer":null,"size":2020,"sizes":{"javascript":2020},"built":true,"codeGenerated":true,"buildTimeExecuted":false,"cached":false,"identifier":"./dist/static/js/runtime.cb956988.js","name":"./dist/static/js/runtime.cb956988.js","nameForCondition":"./dist/static/js/runtime.cb956988.js","index":1,"preOrderIndex":1,"index2":1,"postOrderIndex":1,"cacheable":true,"optional":false,"orphan":false,"issuer":null,"issuerName":null,"issuerPath":null,"failed":false,"errors":0,"warnings":0,"id":648,"issuerId":null,"chunks":[826],"assets":[],"reasons":[{"moduleIdentifier":null,"module":null,"moduleName":null,"resolvedModuleIdentifier":null,"resolvedModule":null,"type":"entry","active":true,"explanation":"","userRequest":"./dist/static/js/runtime.cb956988.js","loc":"index","moduleId":null,"resolvedModuleId":null}],"usedExports":[],"providedExports":null,"optimizationBailout":["Statement (ExpressionStatement) with side effects in source code at 1:0-1975","ModuleConcatenation bailout: Module is not an ECMAScript module"],"depth":0},{"type":"module","moduleType":"javascript/auto","layer":null,"size":508729,"sizes":{"javascript":508729},"built":true,"codeGenerated":true,"buildTimeExecuted":false,"cached":false,"identifier":"./dist/static/js/vendors.365dc8b1.js","name":"./dist/static/js/vendors.365dc8b1.js","nameForCondition":"./dist/static/js/vendors.365dc8b1.js","index":2,"preOrderIndex":2,"index2":2,"postOrderIndex":2,"cacheable":true,"optional":false,"orphan":false,"issuer":null,"issuerName":null,"issuerPath":null,"failed":false,"errors":0,"warnings":0,"id":754,"issuerId":null,"chunks":[826],"assets":[],"reasons":[{"moduleIdentifier":null,"module":null,"moduleName":null,"resolvedModuleIdentifier":null,"resolvedModule":null,"type":"entry","active":true,"explanation":"","userRequest":"./dist/static/js/vendors.365dc8b1.js","loc":"index","moduleId":null,"resolvedModuleId":null}],"usedExports":[],"providedExports":null,"optimizationBailout":["Statement (ExpressionStatement) with side effects in source code at 2:0-508607","ModuleConcatenation bailout: Module is not an ECMAScript module"],"depth":0}],"entrypoints":{"index":{"name":"index","chunks":[826],"assets":[{"name":"web.js","size":518053}],"filteredAssets":0,"assetsSize":518053,"auxiliaryAssets":[],"filteredAuxiliaryAssets":0,"auxiliaryAssetsSize":0,"children":{},"childAssets":{},"isOverSizeLimit":true}},"namedChunkGroups":{"index":{"name":"index","chunks":[826],"assets":[{"name":"web.js","size":518053}],"filteredAssets":0,"assetsSize":518053,"auxiliaryAssets":[],"filteredAuxiliaryAssets":0,"auxiliaryAssetsSize":0,"children":{},"childAssets":{},"isOverSizeLimit":true}},"errors":[],"errorsCount":0,"warnings":[{"message":"configuration\nThe 'mode' option has not been set, webpack will fallback to 'production' for this value.\nSet 'mode' option to 'development' or 'production' to enable defaults for each environment.\nYou can also set it to 'none' to disable any default behavior. Learn more: https://webpack.js.org/configuration/mode/","stack":"NoModeWarning: configuration\nThe 'mode' option has not been set, webpack will fallback to 'production' for this value.\nSet 'mode' option to 'development' or 'production' to enable defaults for each environment.\nYou can also set it to 'none' to disable any default behavior. Learn more: https://webpack.js.org/configuration/mode/\n    at ./node_modules/webpack/lib/WarnNoModeSetPlugin.js:20:30\n    at Hook.eval [as call] (eval at create (./node_modules/tapable/lib/HookCodeFactory.js:19:10), <anonymous>:21:1)\n    at Hook.CALL_DELEGATE [as _call] (./node_modules/tapable/lib/Hook.js:14:14)\n    at Compiler.newCompilation (./node_modules/webpack/lib/Compiler.js:1121:30)\n    at ./node_modules/webpack/lib/Compiler.js:1166:29\n    at Hook.eval [as callAsync] (eval at create (./node_modules/tapable/lib/HookCodeFactory.js:33:10), <anonymous>:6:1)\n    at Hook.CALL_ASYNC_DELEGATE [as _callAsync] (./node_modules/tapable/lib/Hook.js:18:14)\n    at Compiler.compile (./node_modules/webpack/lib/Compiler.js:1161:28)\n    at ./node_modules/webpack/lib/Compiler.js:524:12\n    at Compiler.readRecords (./node_modules/webpack/lib/Compiler.js:986:5)"},{"message":"asset size limit: The following asset(s) exceed the recommended size limit (244 KiB).\nThis can impact web performance.\nAssets: \n  web.js (506 KiB)","stack":"AssetsOverSizeLimitWarning: asset size limit: The following asset(s) exceed the recommended size limit (244 KiB).\nThis can impact web performance.\nAssets: \n  web.js (506 KiB)\n    at ./node_modules/webpack/lib/performance/SizeLimitsPlugin.js:134:7\n    at Hook.eval [as callAsync] (eval at create (./node_modules/tapable/lib/HookCodeFactory.js:33:10), <anonymous>:9:1)\n    at Hook.CALL_ASYNC_DELEGATE [as _callAsync] (./node_modules/tapable/lib/Hook.js:18:14)\n    at ./node_modules/webpack/lib/Compiler.js:882:27\n    at ./node_modules/neo-async/async.js:2818:7\n    at done (./node_modules/neo-async/async.js:3522:9)\n    at alreadyWritten (./node_modules/webpack/lib/Compiler.js:714:8)\n    at ./node_modules/webpack/lib/Compiler.js:802:19\n    at ./node_modules/graceful-fs/graceful-fs.js:123:16\n    at FSReqCallback.readFileAfterClose [as oncomplete] (node:internal/fs/read_file_context:68:3)"},{"message":"entrypoint size limit: The following entrypoint(s) combined asset size exceeds the recommended limit (244 KiB). This can impact web performance.\nEntrypoints:\n  index (506 KiB)\n      web.js\n","stack":"EntrypointsOverSizeLimitWarning: entrypoint size limit: The following entrypoint(s) combined asset size exceeds the recommended limit (244 KiB). This can impact web performance.\nEntrypoints:\n  index (506 KiB)\n      web.js\n\n    at ./node_modules/webpack/lib/performance/SizeLimitsPlugin.js:139:7\n    at Hook.eval [as callAsync] (eval at create (./node_modules/tapable/lib/HookCodeFactory.js:33:10), <anonymous>:9:1)\n    at Hook.CALL_ASYNC_DELEGATE [as _callAsync] (./node_modules/tapable/lib/Hook.js:18:14)\n    at ./node_modules/webpack/lib/Compiler.js:882:27\n    at ./node_modules/neo-async/async.js:2818:7\n    at done (./node_modules/neo-async/async.js:3522:9)\n    at alreadyWritten (./node_modules/webpack/lib/Compiler.js:714:8)\n    at ./node_modules/webpack/lib/Compiler.js:802:19\n    at ./node_modules/graceful-fs/graceful-fs.js:123:16\n    at FSReqCallback.readFileAfterClose [as oncomplete] (node:internal/fs/read_file_context:68:3)"},{"message":"webpack performance recommendations: \nYou can limit the size of your bundles by using import() or require.ensure to lazy load some parts of your application.\nFor more info visit https://webpack.js.org/guides/code-splitting/","stack":"NoAsyncChunksWarning: webpack performance recommendations: \nYou can limit the size of your bundles by using import() or require.ensure to lazy load some parts of your application.\nFor more info visit https://webpack.js.org/guides/code-splitting/\n    at ./node_modules/webpack/lib/performance/SizeLimitsPlugin.js:153:21\n    at Hook.eval [as callAsync] (eval at create (./node_modules/tapable/lib/HookCodeFactory.js:33:10), <anonymous>:9:1)\n    at Hook.CALL_ASYNC_DELEGATE [as _callAsync] (./node_modules/tapable/lib/Hook.js:18:14)\n    at ./node_modules/webpack/lib/Compiler.js:882:27\n    at ./node_modules/neo-async/async.js:2818:7\n    at done (./node_modules/neo-async/async.js:3522:9)\n    at alreadyWritten (./node_modules/webpack/lib/Compiler.js:714:8)\n    at ./node_modules/webpack/lib/Compiler.js:802:19\n    at ./node_modules/graceful-fs/graceful-fs.js:123:16\n    at FSReqCallback.readFileAfterClose [as oncomplete] (node:internal/fs/read_file_context:68:3)"}],"warningsCount":4,"children":[],"name":"web","__statoscope":{"descriptor":{"name":"@statoscope/stats","version":"5.14.1"},"extensions":[{"descriptor":{"name":"@statoscope/stats-extension-package-info","version":"5.25.0","author":{"name":"Sergey Melyukov","url":"https://twitter.com/smelukov"},"homepage":"https://github.com/statoscope/statoscope/","description":"Statoscope extension for collecting package info (e.g. available versions)","adapter":{"name":"@statoscope/webpack-stats-extension-package-info","version":"5.25.1","author":{"name":"Sergey Melyukov","url":"https://twitter.com/smelukov"},"homepage":"https://github.com/statoscope/statoscope/","description":"Webpack adapter for @statoscope/stats-extension-package-info"}},"payload":{"compilations":[{"id":null,"packages":[{"name":"web","instances":[{"path":"","info":{"version":"0.1.0"}}]}]}]}},{"descriptor":{"name":"@statoscope/stats-extension-compressed","version":"5.25.0","author":{"name":"Sergey Melyukov","url":"https://twitter.com/smelukov"},"homepage":"https://github.com/statoscope/statoscope/","description":"Statoscope extension for collecting compressed resource sizes","adapter":{"name":"@statoscope/webpack-stats-extension-compressed","version":"5.25.1","author":{"name":"Sergey Melyukov","url":"https://twitter.com/smelukov"},"homepage":"https://github.com/statoscope/statoscope/","description":"Webpack adapter for @statoscope/stats-extension-compressed"}},"payload":{"compilations":[{"id":"a45386445bf7e6ab4d69","resources":[{"id":"web.js","size":{"compressor":"gzip","size":156643,"meta":{"level":6}}},{"id":"web.js.LICENSE.txt","size":{"compressor":"gzip","size":112,"meta":{"level":6}}},{"id":"./dist/static/js/vendors.365dc8b1.js","size":{"compressor":"gzip","size":153204,"meta":{"level":6}}},{"id":"./dist/static/js/runtime.cb956988.js","size":{"compressor":"gzip","size":1008,"meta":{"level":6}}},{"id":"./dist/static/js/main.c29064ae.js","size":{"compressor":"gzip","size":3778,"meta":{"level":6}}}]}]}}],"context":"/Users/techdeus/src/myfiles/src/game/web"}}